{
  "title": "Security - Authorization - HTTP traffic",
  "description": "Practice configuring Istio's access control for HTTP traffic.",
  "details": {
    "steps": [
      {
        "title": "Intro",
        "text": "step1/text.md"
      },
      {
        "title": "Configure allow-nothing authorization policy",
        "text": "step2/text.md",
        "verify": "step2/verify.sh"
      },
      {
        "title": "Test allow-nothing authorization policy",
        "text": "step3/text.md",
        "verify": "step3/verify.sh"
      },
      {
        "title": "Configure service account for booking-service",
        "text": "step4/text.md",
        "verify": "step4/verify.sh"
      },
      {
        "title": "Configure booking-service authorization policy",
        "text": "step5/text.md",
        "verify": "step5/verify.sh"
      },
      {
        "title": "Configure notification-service authorization policy",
        "text": "step6/text.md",
        "verify": "step6/verify.sh"
      },
      {
        "title": "Test authorization policies",
        "text": "step7/text.md",
        "verify": "step7/verify.sh"
      }
    ],
    "finish": {
      "text": "finish/finish.md"
    },
    "intro": {
      "text": "init/init.md",
      "background": "init/background.sh",
      "foreground": "init/foreground.sh"
    },
    "assets": {
      "host01": [
        {
          "file": "wait-background.sh",
          "target": "/ks",
          "chmod": "+x"
        },
        {
          "file": "check-utils.sh",
          "target": "/tmp",
          "chmod": "+x"
        },
        {
          "file": "demo.yaml",
          "target": "/tmp",
          "chmod": "+x"
        },
        {
          "file": "notification-deployment.yaml",
          "target": "/tmp",
          "chmod": "+x"
        },
        {
          "file": "booking-deployment.yaml",
          "target": "/tmp",
          "chmod": "+x"
        }
      ]
    }
  },
  "backend": {
    "imageid": "kubernetes-kubeadm-1node"
  }
}